{"births": [
{"name": "William_Holman_Hunt", "date": "1827-04-02", "factors": [2,2,2,2,2,101,739]},
{"name": "Uli_Hoeneß", "date": "1952-01-05", "factors": [2,2,2,2,2,13,5851]},
{"name": "Thomas_Gravesen", "date": "1976-03-11", "factors": [2,2,2,2,2,97,787]},
{"name": "Terry_O\u0027Quinn", "date": "1952-07-15", "factors": [2,2,2,2,2,7,10867]},
{"name": "Steve_Wozniak", "date": "1950-08-11", "factors": [2,2,2,2,2,3,25349]},
{"name": "Sirhan_Sirhan", "date": "1944-03-19", "factors": [2,2,2,2,2,2,37987]},
{"name": "Sergei_Bondarchuk", "date": "1920-09-25", "factors": [2,2,2,2,2,2,37853]},
{"name": "Rudolf_Kirchschläger", "date": "1915-03-20", "factors": [2,2,2,2,2,67,1129]},
{"name": "Romelu_Lukaku", "date": "1993-05-13", "factors": [2,2,2,2,2,5,15307]},
{"name": "Robert_Patrick", "date": "1958-11-05", "factors": [2,2,2,2,2,13,5857]},
{"name": "Rene_Krhin", "date": "1990-05-21", "factors": [2,2,2,2,2,113,677]},
{"name": "Peter_Higgs", "date": "1929-05-29", "factors": [2,2,2,2,2,5,15161]},
{"name": "Pedro_Almodóvar", "date": "1949-09-25", "factors": [2,2,2,2,2,13,5849]},
{"name": "Ottmar_Hitzfeld", "date": "1949-01-12", "factors": [2,2,2,2,2,3,25343]},
{"name": "Maumoon_Abdul_Gayoom", "date": "1937-12-29", "factors": [2,2,2,2,2,3,25301]},
{"name": "Mary_McAleese", "date": "1951-06-27", "factors": [2,2,2,2,2,19,4003]},
{"name": "Mariah_Carey", "date": "1970-03-27", "factors": [2,2,2,2,2,13,5867]},
{"name": "Luiz_Felipe_Scolari", "date": "1948-11-09", "factors": [2,2,2,2,2,7,10861]},
{"name": "Ludwig_von_Mises", "date": "1881-09-29", "factors": [2,2,2,2,2,3,25087]},
{"name": "Liv_Ullmann", "date": "1938-12-16", "factors": [2,2,2,2,2,2,37957]},
{"name": "Lao_She", "date": "1899-02-03", "factors": [2,2,2,2,2,3,25153]},
{"name": "Kevin_Phillips_(footballer)", "date": "1973-07-25", "factors": [2,2,2,2,2,137,557]},
{"name": "Julia_Louis-Dreyfus", "date": "1961-01-13", "factors": [2,2,2,2,2,2,38083]},
{"name": "John_Malkovich", "date": "1953-12-09", "factors": [2,2,2,2,2,5,15217]},
{"name": "John_Locke", "date": "1632-08-29", "factors": [2,2,2,2,2,2,36209]},
{"name": "Jean-Marie_Lehn", "date": "1939-09-30", "factors": [2,2,2,2,2,23,3301]},
{"name": "Jackson_Rathbone", "date": "1984-12-14", "factors": [2,2,2,2,2,11,6949]},
{"name": "I._M._Pei", "date": "1917-04-26", "factors": [2,2,2,2,2,17,4451]},
{"name": "Hu_Jia_(activist)", "date": "1973-07-25", "factors": [2,2,2,2,2,137,557]},
{"name": "Haruki_Murakami", "date": "1949-01-12", "factors": [2,2,2,2,2,3,25343]},
{"name": "Guy_Demel", "date": "1981-06-13", "factors": [2,2,2,2,2,19,4021]},
{"name": "Gus_Grissom", "date": "1926-04-03", "factors": [2,2,2,2,2,17,4457]},
{"name": "Gao_Xingjian", "date": "1940-01-04", "factors": [2,2,2,2,2,2,37963]},
{"name": "Ferdinand_Buisson", "date": "1841-12-20", "factors": [2,2,2,2,2,239,313]},
{"name": "Erich_Raeder", "date": "1876-04-24", "factors": [2,2,2,2,2,139,541]},
{"name": "Elle_Fanning", "date": "1998-04-09", "factors": [2,2,2,2,2,191,401]},
{"name": "Elizabeth_Mitchell", "date": "1970-03-27", "factors": [2,2,2,2,2,13,5867]},
{"name": "Eddie_Vedder", "date": "1964-12-23", "factors": [2,2,2,2,2,17,4483]},
{"name": "Debby_Ryan", "date": "1993-05-13", "factors": [2,2,2,2,2,5,15307]},
{"name": "David_Lynch", "date": "1946-01-20", "factors": [2,2,2,2,2,5,15199]},
{"name": "Connie_Nielsen", "date": "1965-07-03", "factors": [2,2,2,2,2,199,383]},
{"name": "Chris_Evans_(actor)", "date": "1981-06-13", "factors": [2,2,2,2,2,19,4021]},
{"name": "Charles_X_of_France", "date": "1757-10-09", "factors": [2,2,2,2,2,2,36923]},
{"name": "Billy_Ray_Cyrus", "date": "1961-08-25", "factors": [2,2,2,2,2,3,25391]},
{"name": "Bernard_Montgomery,_1st_Viscount_Montgomery_of_Alamein", "date": "1887-11-17", "factors": [2,2,2,2,2,71,1061]},
{"name": "Benni_McCarthy", "date": "1977-12-11", "factors": [2,2,2,2,2,3,25453]},
{"name": "Benedict_Arnold", "date": "1741-01-14", "factors": [2,2,2,2,2,5,14731]},
{"name": "Augustus_De_Morgan", "date": "1806-06-27", "factors": [2,2,2,2,2,2,37201]},
{"name": "Art_Tatum", "date": "1909-10-13", "factors": [2,2,2,2,2,11,6871]},
{"name": "Ante_Gotovina", "date": "1955-10-12", "factors": [2,2,2,2,2,2,38053]},
null ] };
