{"births": [
{"name": "Thorbjørn_Jagland", "date": "1950-11-05", "factors": [2,5,163,1493]},
{"name": "Stanislav_Petrov", "date": "1939-09-09", "factors": [5,11,163,271]},
{"name": "Roger_Martin_du_Gard", "date": "1881-03-23", "factors": [2,83,89,163]},
{"name": "Paul_Éluard", "date": "1895-12-14", "factors": [13,17,67,163]},
{"name": "Karolos_Papoulias", "date": "1929-06-04", "factors": [2,7,163,1063]},
{"name": "Julian_Huxley", "date": "1887-06-22", "factors": [2,2,163,3697]},
{"name": "Jacobus_Henricus_van_\u0027t_Hoff", "date": "1852-08-30", "factors": [2,5,163,1471]},
{"name": "Horst_Seehofer", "date": "1949-07-04", "factors": [11,23,59,163]},
{"name": "Hermann_Staudinger", "date": "1881-03-23", "factors": [2,83,89,163]},
{"name": "Hafez_al-Assad", "date": "1930-10-06", "factors": [5,13,163,229]},
{"name": "Federico_Fellini", "date": "1920-01-20", "factors": [7,11,163,193]},
{"name": "Emmanuel_Eboué", "date": "1983-06-04", "factors": [3,3,163,1667]},
{"name": "Charlene,_Princess_of_Monaco", "date": "1978-01-25", "factors": [3,19,163,263]},
null ] };
